[
  {
    "순위": 1,
    "제목": "이것은 샘플 데이터입니다 (실제 데이터를 보려면 run_all.py를 실행하세요)",
    "추천점수": 99,
    "키워드": "샘플, 테스트",
    "출처": "시스템",
    "유튜브_URL": "",
    "뉴스기사_URL": "",
    "업로드일": "2024-01-01"
  },
  {
    "순위": 2,
    "제목": "유튜브 샘플 항목",
    "추천점수": 80,
    "키워드": "유튜브, 키워드",
    "출처": "유튜브",
    "유튜브_URL": "https://youtube.com",
    "뉴스기사_URL": "",
    "업로드일": "2024-01-02"
  },
  {
    "순위": 3,
    "제목": "뉴스 샘플 항목",
    "추천점수": 75,
    "키워드": "뉴스, 속보",
    "출처": "구글뉴스",
    "유튜브_URL": "",
    "뉴스기사_URL": "https://google.com",
    "업로드일": "2024-01-03"
  }
]
